gtfs_map_matcher/__init__.py
gtfs_map_matcher/data/auckland_gtfs_sample.zip
gtfs_map_matcher/main.py
gtfs_map_matcher/matchers.py
gtfs_map_matcher-3.0.1.dist-info/WHEEL
gtfs_map_matcher-3.0.1.dist-info/METADATA
gtfs_map_matcher-3.0.1.dist-info/RECORD
