Metadata-Version: 2.1
Name: gtfs-map-matcher
Version: 3.0.1
Summary: A Python 3.8+ library to mshapes to Open Street Map roads
License: MIT
Author: Alex Raichev
Author-email: araichev@mrcagney.com
Requires-Python: >=3.8,<4.0
Classifier: License :: OSI Approved :: MIT License
Classifier: Programming Language :: Python :: 3
Classifier: Programming Language :: Python :: 3.8
Classifier: Programming Language :: Python :: 3.9
Requires-Dist: loguru (>=0.5.3,<0.6.0)
Requires-Dist: pandas (>=1.1.3,<2.0.0)
Requires-Dist: polyline (>=1.4.0,<2.0.0)
Requires-Dist: requests-futures (>=1.0.0,<2.0.0)
